ezflask/__init__.py
ezflask-0.0.6.dist-info/LICENSE
ezflask-0.0.6.dist-info/METADATA
ezflask-0.0.6.dist-info/WHEEL
ezflask-0.0.6.dist-info/top_level.txt
ezflask-0.0.6.dist-info/RECORD
