Metadata-Version: 2.1
Name: ezflask
Version: 0.0.6
Summary: The fastest way to make a website
Home-page: https://github.com/SmartMozart/ezflask
Author: SmartMozart
Author-email: zacsengines@yahoo.com
License: UNKNOWN
Project-URL: Bug Tracker, https://github.com/SmartMozart/ezflask/issues
Platform: UNKNOWN
Classifier: Programming Language :: Python :: 3
Classifier: License :: OSI Approved :: MIT License
Classifier: Operating System :: OS Independent
Requires-Python: >=3.6
License-File: LICENSE
Requires-Dist: flask
Requires-Dist: markupsafe
